prompt_regress/cli.py
prompt_regress/core.py
prompt_regress/metrics/__init__.py
prompt_regress/metrics/similarity.py
prompt_regress/models/__init__.py
prompt_regress/models/anthropic_provider.py
prompt_regress/models/base.py
prompt_regress/models/local_provider.py
prompt_regress/models/openai_provider.py
prompt_regress-0.1.0.dist-info/METADATA
prompt_regress-0.1.0.dist-info/WHEEL
prompt_regress-0.1.0.dist-info/entry_points.txt
prompt_regress-0.1.0.dist-info/top_level.txt
prompt_regress-0.1.0.dist-info/RECORD
