Metadata-Version: 2.4
Name: prompt-regress
Version: 0.1.0
Summary: A cli tool for prompt regression testing
Requires-Python: >=3.12
Requires-Dist: anthropic>=0.52.2
Requires-Dist: click>=8.2.1
Requires-Dist: hf-xet>=1.1.3
Requires-Dist: ollama>=0.5.1
Requires-Dist: openai>=1.84.0
Requires-Dist: pytest>=8.4.0
Requires-Dist: pytest-asyncio>=1.0.0
Requires-Dist: pyyaml>=6.0.2
Requires-Dist: rapidfuzz>=3.13.0
Requires-Dist: sentence-transformers>=4.1.0
Requires-Dist: tiktoken>=0.9.0
